squeeze_rest/__init__.py
squeeze_rest/app.py
squeeze_rest/library.py
squeeze_rest/player.py
squeeze_rest-0.2.1.dist-info/METADATA
squeeze_rest-0.2.1.dist-info/WHEEL
squeeze_rest-0.2.1.dist-info/RECORD
