Metadata-Version: 2.1
Name: squeeze-rest
Version: 0.2.1
Summary: A ReST API wrapper for the Logitech Media Server/SqueezeBox JSON-RPC API.
License: MIT
Author: Simon Redding
Author-email: s1m0n.r3dd1ng@gmail.com
Requires-Python: >=3.11,<4.0
Classifier: License :: OSI Approved :: MIT License
Classifier: Programming Language :: Python :: 3
Classifier: Programming Language :: Python :: 3.11
Classifier: Programming Language :: Python :: 3.12
Requires-Dist: Flask (>=3.0.0,<4.0.0)
Requires-Dist: squeeze-jrpc (>=0.2.0,<0.3.0)
